smartfit_booking/__init__.py
smartfit_booking/data_access_api.py
smartfit_booking/formatter.py
smartfit_booking/logger.py
smartfit_booking/storage.py
smartfit_booking/website_bot.py
smartfit_booking-0.0.3.dist-info/LICENSE
smartfit_booking-0.0.3.dist-info/METADATA
smartfit_booking-0.0.3.dist-info/WHEEL
smartfit_booking-0.0.3.dist-info/top_level.txt
smartfit_booking-0.0.3.dist-info/RECORD
