Metadata-Version: 2.1
Name: smartfit-booking
Version: 0.0.3
Summary: Smart Fit gym booking package
Home-page: UNKNOWN
Author: Stiven Ramírez Arango
Author-email: stivenramireza@gmail.com
License: UNKNOWN
Platform: UNKNOWN
Requires-Python: >=3.6
Requires-Dist: selenium (==3.141.0)
Requires-Dist: requests (==2.25.1)
Requires-Dist: python-dotenv (==0.15.0)
